{
   "format_version" : "1.13.0",
   "minecraft:biome" : {
      "components" : {
         "minecraft:surface_parameters" : {
            "air_material" : "minecraft:air",
            "default_surface" : {
               "mid_material" : "badger:block_slag",
               "top_material" : "badger:block_slag"
            },
            "foundation_material" : "badger:block_slag",
            "sea_floor_depth" : 4,
            "sea_floor_material" : "badger:block_slag",
            "sea_material" : "badger:block_slag"
         }
      },
      "description" : {
         "identifier" : "denether"
      }
   }
}
