{
  "format_version": "1.8.0", 
  "minecraft:block": {
    "description": {
      "identifier": "badger:block_deco_xp_flame", 
      "material": "badger_stone"
    }, 
    "components": {
      "minecraft:block_shape": {
        "shape": "empty", 
        "directional_texture": false, 
        "directional_shape": true, 
        "collision_shape": "block"
      }, 
      "badger:block_damage_receiver_material": {
        "material": "block"
      }, 
      "minecraft:block_light_emission": {
        "emission": 0.65
      }, 
      "minecraft:destroy_time": {
        "value": 10
      }, 
      "badger:terrain_type": {
        "terrain": "stone"
      }
    }
  }
}