{
  "format_version": "1.8.0",
  "minecraft:block": {
    "description": {
      "identifier": "badger:block_pillar_plant_coraltube_b_top",
      "material": "badger_wood"
    },
    "components": {
      "minecraft:block_shape": {
        "shape": "upright",
        "directional_texture": false,
        "directional_shape": true
      },
      "badger:block_damage_receiver_material": {
        "material": "block"
      },
      "badger:block_type": {
        "tags": [
          "gatherable_stone"
        ]
      }
    }
  }
}